README.md
setup.py
gruut_lang_de/VERSION
gruut_lang_de/__init__.py
gruut_lang_de/lexicon.db
gruut_lang_de.egg-info/PKG-INFO
gruut_lang_de.egg-info/SOURCES.txt
gruut_lang_de.egg-info/dependency_links.txt
gruut_lang_de.egg-info/top_level.txt
gruut_lang_de/espeak/lexicon.db
gruut_lang_de/espeak/g2p/model.crf
gruut_lang_de/g2p/model.crf